speterlin_crypto/__init__.py
speterlin_crypto/module1.py
speterlin_crypto-1.0.6.dist-info/licenses/LICENSE
speterlin_crypto-1.0.6.dist-info/METADATA
speterlin_crypto-1.0.6.dist-info/WHEEL
speterlin_crypto-1.0.6.dist-info/top_level.txt
speterlin_crypto-1.0.6.dist-info/RECORD
